testaid/__init__.py
testaid/ansibleres.py
testaid/ansiblerun.py
testaid/boilerplate.py
testaid/exceptions.py
testaid/jsonvars.py
testaid/moleculebook.py
testaid/moleculeenv.py
testaid/moleculelog.py
testaid/moleculeplay.py
testaid/pathlist.py
testaid/plugin.py
testaid/templates.py
testaid/testpass.py
testaid/testvars.py
testaid-0.15.1.dist-info/LICENSE
testaid-0.15.1.dist-info/METADATA
testaid-0.15.1.dist-info/WHEEL
testaid-0.15.1.dist-info/entry_points.txt
testaid-0.15.1.dist-info/top_level.txt
testaid-0.15.1.dist-info/RECORD
