Metadata-Version: 2.1
Name: testaid
Version: 0.15.1
Summary: Fixtures for ansible, testinfra and molecule
Home-page: https://github.com/RebelCodeBase/testaid
Author: RebelCodeBase
Author-email: rebelcodebase@riseup.net
License: Apache-2.0
Platform: any
Classifier: Programming Language :: Python
Classifier: Programming Language :: Python :: 3
Classifier: Intended Audience :: Information Technology
Classifier: Intended Audience :: Developers
Classifier: Intended Audience :: System Administrators
Classifier: License :: OSI Approved :: MIT License
Classifier: Operating System :: POSIX
Classifier: Topic :: Software Development :: Libraries :: Python Modules
Classifier: Topic :: Software Development :: Testing
Classifier: Topic :: System :: Systems Administration
Classifier: Framework :: Pytest
Requires-Dist: ansible (>=2.8)
